Subtractor/FullSubtractor.v
// Diff = A XOR B XOR Borrowin
// Borrowout = A'(B XOR Borrowin) + B.Borrowin
// There's some problem with the outputs. Borrowout isn't showing correct values once there are more than 1 true inputs. Fix later.
// It might be due to operator precedence order(s) but I split it into c-f but its still misbehaving.
module fs
(
    input a,b,borrowin,
    output diff,borrowout
);
wire c,d,e,f;
assign diff = a ^ b ^ borrowin;
assign c = ~a;
assign d = b ^ borrowin;
assign e = b & borrowin;
assign f = c & d;
assign borrowout = (e | f);

endmodule

Subtractor/FullSubtractor_TB.v
module fs_tb;
reg A,B,Borrowin;
wire Diff,Borrowout;

fs bring
(
    .a(A),
    .b(B),
    .borrowin(Borrowin),
    .diff(Diff),
    .borrowout(Borrowout)
);

initial begin
    $dumpfile("fs.vcd");
    $dumpvars(0,fs_tb);

    A=0;B=0;Borrowin=0;
    #10;
    A=0;B=0;Borrowin=1;
    #10;
    A=0;B=1;Borrowin=0;
    #10;
    A=0;B=1;Borrowin=1;
    #10;
    A=1;B=0;Borrowin=0;
    #10;
    A=1;B=0;Borrowin=1;
    #10;
    A=1;B=1;Borrowin=0;
    #10;
    A=1;B=1;Borrowin=1;
    #10;

    $finish;
end
endmodule

Subtractor/fs.vcd
$date
	Wed Feb  4 15:39:39 2026
$end
$version
	Icarus Verilog
$end
$timescale
	1s
$end
$scope module fs_tb $end
$var wire 1 ! Diff $end
$var wire 1 " Borrowout $end
$var reg 1 # A $end
$var reg 1 $ B $end
$var reg 1 % Borrowin $end
$scope module bring $end
$var wire 1 # a $end
$var wire 1 $ b $end
$var wire 1 % borrowin $end
$var wire 1 " borrowout $end
$var wire 1 & c $end
$var wire 1 ' d $end
$var wire 1 ! diff $end
$var wire 1 ( e $end
$var wire 1 ) f $end
$upscope $end
$upscope $end
$enddefinitions $end
$comment Show the parameter values. $end
$dumpall
$end
#0
$dumpvars
0)
0(
0'
1&
0%
0$
0#
0"
0!
$end
#10
1"
1)
1!
1'
1%
#20
0%
1$
#30
0)
0!
0'
1(
1%
#40
0"
1!
0(
0&
0%
0$
1#
#50
0!
1'
1%
#60
0%
1$
#70
1"
1!
0'
1(
1%
